solana_fcg_tool/README.md
solana_fcg_tool/__init__.py
solana_fcg_tool/cli.py
solana_fcg_tool/funcation-anayzer.py
solana_fcg_tool/interface.py
solana_fcg_tool/struct-anayzer.py
solana_fcg_tool/bin/rust-analyzer
solana_fcg_tool/bin/rust-analyzer-linux-x86_64
solana_fcg_tool/bin/rust-analyzer-macos-aarch64
solana_fcg_tool/bin/rust-analyzer-macos-x86_64
solana_fcg_tool/bin/rust-analyzer-windows-x86_64.exe
solana_fcg_tool/output/2025-01-pump-science_call_graph.json
solana_fcg_tool-1.0.6.dist-info/METADATA
solana_fcg_tool-1.0.6.dist-info/WHEEL
solana_fcg_tool-1.0.6.dist-info/entry_points.txt
solana_fcg_tool-1.0.6.dist-info/top_level.txt
solana_fcg_tool-1.0.6.dist-info/RECORD
