Metadata-Version: 2.1
Name: solana-fcg-tool
Version: 1.0.6
Summary: A comprehensive Rust project analyzer for Solana development with multi-platform support
Home-page: https://github.com/yourusername/solana-fcg-tool
Author: Solana Analyzer Team
Author-email: your.email@example.com
Maintainer: Solana Analyzer Team
License: MIT
Project-URL: Homepage, https://github.com/your-repo/solana-analyzer
Project-URL: Repository, https://github.com/your-repo/solana-analyzer.git
Project-URL: Issues, https://github.com/your-repo/solana-analyzer/issues
Keywords: rust,analyzer,solana,blockchain,code-analysis
Classifier: Development Status :: 4 - Beta
Classifier: Intended Audience :: Developers
Classifier: Topic :: Software Development :: Code Generators
Classifier: Topic :: Software Development :: Libraries :: Python Modules
Classifier: License :: OSI Approved :: MIT License
Classifier: Programming Language :: Python :: 3
Classifier: Programming Language :: Python :: 3.8
Classifier: Programming Language :: Python :: 3.9
Classifier: Programming Language :: Python :: 3.10
Classifier: Programming Language :: Python :: 3.11
Classifier: Programming Language :: Rust
Requires-Python: >=3.7
Provides-Extra: dev
Requires-Dist: pytest>=6.0; extra == "dev"
Requires-Dist: pytest-cov; extra == "dev"
Requires-Dist: black; extra == "dev"
Requires-Dist: flake8; extra == "dev"
Requires-Dist: mypy; extra == "dev"
